fitin/__init__.py
fitin/fitin.py
fitin-0.3.0.dist-info/WHEEL
fitin-0.3.0.dist-info/METADATA
fitin-0.3.0.dist-info/RECORD
