Metadata-Version: 2.1
Name: fitin
Version: 0.3.0
Summary: Simple config management, making it easy to write services that fit in.
License: MIT
Author: peder2911
Author-email: pglandsverk@gmail.com
Requires-Python: >=3.8,<4.0
Classifier: License :: OSI Approved :: MIT License
Classifier: Programming Language :: Python :: 3
Classifier: Programming Language :: Python :: 3.8
Classifier: Programming Language :: Python :: 3.9
Requires-Dist: azure-appconfiguration (>=1.1.1,<2.0.0)
Requires-Dist: azure-identity (>=1.5.0,<2.0.0)
Requires-Dist: azure-keyvault-secrets (>=4.2.0,<5.0.0)
Requires-Dist: environs (>=9.3.1,<10.0.0)
